claude_sync/__init__.py
claude_sync/cli.py
claude_sync/compatibility.py
claude_sync/profiles.py
claude_sync/sync.py
claude_sync/templates.py
claude_remote-0.1.1.dist-info/METADATA
claude_remote-0.1.1.dist-info/WHEEL
claude_remote-0.1.1.dist-info/entry_points.txt
claude_remote-0.1.1.dist-info/top_level.txt
claude_remote-0.1.1.dist-info/RECORD
