Metadata-Version: 2.4
Name: claude-remote
Version: 0.1.1
Summary: Sync local Claude Code environments to remote machines
Author: Gokul Ganesan
License: MIT
Project-URL: Homepage, https://github.com/xeiroh/claude-sync
Project-URL: Repository, https://github.com/xeiroh/claude-sync
Keywords: claude,sync,remote,gpu,cloud
Classifier: Development Status :: 3 - Alpha
Classifier: Intended Audience :: Developers
Classifier: License :: OSI Approved :: MIT License
Classifier: Programming Language :: Python :: 3
Classifier: Programming Language :: Python :: 3.10
Classifier: Programming Language :: Python :: 3.11
Classifier: Programming Language :: Python :: 3.12
Requires-Python: >=3.10
Requires-Dist: paramiko>=3.0.0
Requires-Dist: jinja2>=3.1.0
Provides-Extra: dev
Requires-Dist: pytest>=7.0.0; extra == "dev"
Requires-Dist: pytest-cov>=4.0.0; extra == "dev"
Requires-Dist: black>=23.0.0; extra == "dev"
Requires-Dist: ruff>=0.1.0; extra == "dev"
Requires-Dist: mypy>=1.0.0; extra == "dev"
